editpyxl/__init__.py
editpyxl/cell.py
editpyxl/constants.py
editpyxl/util.py
editpyxl/workbook.py
editpyxl/worksheet.py
editpyxl/tests/__init__.py
editpyxl/tests/test_write.py
editpyxl-0.1.10.dist-info/AUTHORS.rst
editpyxl-0.1.10.dist-info/LICENCE.rst
editpyxl-0.1.10.dist-info/METADATA
editpyxl-0.1.10.dist-info/WHEEL
editpyxl-0.1.10.dist-info/top_level.txt
editpyxl-0.1.10.dist-info/RECORD
