Metadata-Version: 2.1
Name: editpyxl
Version: 0.1.10
Summary: A Python library to edit Excel 2007 xlsx/xlsm files
Home-page: http://editpyxl.readthedocs.org
Author: See AUTHORS
Author-email: web@myemptybucket.com
License: MIT/Expat
Download-URL: http://bitbucket.org/amorris/editpyxl/downloads
Platform: UNKNOWN
Classifier: Development Status :: 3 - Alpha
Classifier: Operating System :: MacOS :: MacOS X
Classifier: Operating System :: Microsoft :: Windows
Classifier: Operating System :: POSIX
Classifier: License :: OSI Approved :: MIT License
Classifier: Programming Language :: Python
Classifier: Programming Language :: Python :: 2.6
Classifier: Programming Language :: Python :: 2.7
Classifier: Programming Language :: Python :: 3.2
Classifier: Programming Language :: Python :: 3.3
Classifier: Programming Language :: Python :: 3.4
Classifier: Programming Language :: Python :: 3.5
Classifier: Programming Language :: Python :: 3.6
Classifier: Programming Language :: Python :: 3.7
Classifier: Programming Language :: Python :: 3.8
Classifier: Programming Language :: Python :: 3.9
Classifier: Programming Language :: Python :: 3.10
Requires: python (>=2.6.0)
Requires: lxml (>=4.1.1)
License-File: LICENCE.rst
License-File: AUTHORS.rst
Requires-Dist: lxml
